sequence2bit8lv/state2bit/state.v
module state (q,stop,show,reset,clk);
    output [1:0] q;
    input stop,show,reset,clk;
    wire [1:0] qin;
    wire stopToEn;

    not n1 (stopToEn,stop);
    countup2bit c1 (qin,stopToEn,reset,clk);
    and a1 (q[1],qin[1],show);
    and a2 (q[0],qin[0],show);
endmodule

module countup2bit (q, en, reset, clk);
	output [1:0] q;
	input en, clk, reset;
	wire t0,t1;

    and a1 (t0,1'b1,en);
    and a2 (t1,q[0],en);
	T_FF tff0 (q[0], t0, reset, clk);
	T_FF tff1 (q[1], t1, reset, clk);
endmodule

module T_FF (q, t, reset, clk);
	output q;
	input t,reset,clk;
	wire d;

	xor x1(d,q,t);
	D_FF d1(q,d,reset,clk);
endmodule

module D_FF (q, d, reset, clk);
	output q;
	input d,reset,clk;
	reg q;
	
	always @(posedge reset or posedge clk)
		if (reset)
  			q <= 1'b0;
		else
  			q <= d;
endmodule

sequence2bit8lv/state2bit/stiState.v
module stimulus;
	reg stop,show,reset,clk;
	wire [1:0] q;

    state s (q,stop,show,reset,clk);
	
	initial
		begin
			$dumpfile("stateTD.vcd");
			$dumpvars(0,stimulus);
            stop = 1'b0;
            show = 1'b0;
            reset = 1'b1;
			clk = 1'b1;     
		end		
	always 
		#5 clk = ~clk;
	initial
        begin
            #10 reset = 1'b0;
            #10 show = 1'b1;
            #100 stop = 1'b1;
            #50 $finish;
        end
	initial 
		$monitor ($time, " q1=%b q0=%b stop=%d show=%d reset=%d CLK=%d",q[1],q[0],stop,show,reset,clk);
endmodule

sequence2bit8lv/state2bit/stateTD.vcd
$date
	Thu Oct 13 17:51:51 2022
$end
$version
	Icarus Verilog
$end
$timescale
	1s
$end
$scope module stimulus $end
$var wire 2 ! q [1:0] $end
$var reg 1 " clk $end
$var reg 1 # reset $end
$var reg 1 $ show $end
$var reg 1 % stop $end
$scope module s $end
$var wire 1 " clk $end
$var wire 1 # reset $end
$var wire 1 $ show $end
$var wire 1 % stop $end
$var wire 1 & stopToEn $end
$var wire 2 ' qin [1:0] $end
$var wire 2 ( q [1:0] $end
$scope module c1 $end
$var wire 1 " clk $end
$var wire 1 & en $end
$var wire 1 # reset $end
$var wire 1 ) t0 $end
$var wire 1 * t1 $end
$var wire 2 + q [1:0] $end
$scope module tff0 $end
$var wire 1 " clk $end
$var wire 1 , d $end
$var wire 1 # reset $end
$var wire 1 ) t $end
$var wire 1 - q $end
$scope module d1 $end
$var wire 1 " clk $end
$var wire 1 , d $end
$var wire 1 # reset $end
$var reg 1 - q $end
$upscope $end
$upscope $end
$scope module tff1 $end
$var wire 1 " clk $end
$var wire 1 . d $end
$var wire 1 # reset $end
$var wire 1 * t $end
$var wire 1 / q $end
$scope module d1 $end
$var wire 1 " clk $end
$var wire 1 . d $end
$var wire 1 # reset $end
$var reg 1 / q $end
$upscope $end
$upscope $end
$upscope $end
$upscope $end
$upscope $end
$enddefinitions $end
$comment Show the parameter values. $end
$dumpall
$end
#0
$dumpvars
0/
0.
0-
1,
b0 +
0*
1)
b0 (
b0 '
1&
0%
0$
1#
1"
b0 !
$end
#5
0"
#10
1.
1*
0,
b1 '
b1 +
1-
1"
0#
#15
0"
#20
0*
1,
1.
0-
b10 '
b10 +
1/
b10 !
b10 (
1"
1$
#25
0"
#30
0.
1*
b11 !
b11 (
0,
b11 '
b11 +
1-
1"
#35
0"
#40
0*
b0 !
b0 (
1,
0.
0-
b0 '
b0 +
0/
1"
#45
0"
#50
1.
1*
b1 !
b1 (
0,
b1 '
b1 +
1-
1"
#55
0"
#60
0*
b10 !
b10 (
1,
1.
0-
b10 '
b10 +
1/
1"
#65
0"
#70
0.
1*
b11 !
b11 (
0,
b11 '
b11 +
1-
1"
#75
0"
#80
0*
b0 !
b0 (
1,
0.
0-
b0 '
b0 +
0/
1"
#85
0"
#90
1.
1*
b1 !
b1 (
0,
b1 '
b1 +
1-
1"
#95
0"
#100
0*
b10 !
b10 (
1,
1.
0-
b10 '
b10 +
1/
1"
#105
0"
#110
0.
1*
b11 !
b11 (
0,
b11 '
b11 +
1-
1"
#115
0"
#120
b0 !
b0 (
0-
b0 '
b0 +
0/
0,
0.
0)
0*
0&
1"
1%
