2-to-1_MUX/mux_21.v
 //-----------------------------------------------------
 // Design Name : 2-to-1 mux
 // File Name   : mux_21.v
 // Function    : 2:1 Mux using Logic Gates
 // Coder       : Paskorn Champrasert
 // Date 		: July 23, 2012
 //-----------------------------------------------------
 module  mux_2to1(
 mux_out    , // Mux output
 din_0      , // Mux first input
 din_1      , // Mux Second input
 sel         // Select input
 );
 //-----------Input Ports---------------
 input din_0, din_1, sel ;
 //-----------Output Ports---------------
 output mux_out;
 //------------Internal Variables--------
 wire  w_not1, w_and1, w_and2;
 
 //-------------Code Start-----------------
 not not1(w_not1,sel);
 and and1(w_and1,w_not1,din_0);
 and and2(w_and2,sel,din_1);
 or or1(mux_out,w_and1,w_and2);
 
 endmodule //End Of Module mux

2-to-1_MUX/Stimulus.v
module stimulus;
	reg sel;
	reg din_0,din_1;
	wire mux_out;
	// instantiate the design block
	mux_2to1 mux1(mux_out, din_0,din_1,sel);
	
	// control the signals that drives the design block
	initial
		begin
			$dumpfile("MUXTimeDiagram.vcd");
			$dumpvars(0,stimulus);
			din_0 = 1'b0;  // set din_0 to 0
			din_1 = 1'b1;  // set din_1 to 1
			sel   = 1'b0;  // set sel to 0
		end		
	always 
		#5 sel = ~sel; // toggle sel every 5 time units
	
	
	initial
	begin
		#20 begin
			din_0 = 1'b1;  // set din_0 to 0
			din_1 = 1'b0;  // set din_1 to 1
			end
		#20 begin
			din_0 = 1'b0;  // set din_0 to 0
			din_1 = 1'b1;  // set din_1 to 1
			end
			
		#100 $finish;
	end
	initial 
		$monitor ($time, " Output d1=%d d2=%d sel=%d mux=%d",din_0,din_1, sel, mux_out);
 endmodule

2-to-1_MUX/MUXTimeDiagram.vcd
$date
	Fri Sep 23 15:05:16 2022
$end
$version
	Icarus Verilog
$end
$timescale
	1s
$end
$scope module stimulus $end
$var wire 1 ! mux_out $end
$var reg 1 " din_0 $end
$var reg 1 # din_1 $end
$var reg 1 $ sel $end
$scope module mux1 $end
$var wire 1 " din_0 $end
$var wire 1 # din_1 $end
$var wire 1 ! mux_out $end
$var wire 1 $ sel $end
$var wire 1 % w_and1 $end
$var wire 1 & w_and2 $end
$var wire 1 ' w_not1 $end
$upscope $end
$upscope $end
$enddefinitions $end
$comment Show the parameter values. $end
$dumpall
$end
#0
$dumpvars
1'
0&
0%
0$
1#
0"
0!
$end
#5
1!
0'
1&
1$
#10
0!
1'
0&
0$
#15
1!
0'
1&
1$
#20
1%
1!
1'
0&
0$
0#
1"
#25
0!
0%
0'
1$
#30
1!
1%
1'
0$
#35
0!
0%
0'
1$
#40
1'
0$
1#
0"
#45
1!
0'
1&
1$
#50
0!
1'
0&
0$
#55
1!
0'
1&
1$
#60
0!
1'
0&
0$
#65
1!
0'
1&
1$
#70
0!
1'
0&
0$
#75
1!
0'
1&
1$
#80
0!
1'
0&
0$
#85
1!
0'
1&
1$
#90
0!
1'
0&
0$
#95
1!
0'
1&
1$
#100
0!
1'
0&
0$
#105
1!
0'
1&
1$
#110
0!
1'
0&
0$
#115
1!
0'
1&
1$
#120
0!
1'
0&
0$
#125
1!
0'
1&
1$
#130
0!
1'
0&
0$
#135
1!
0'
1&
1$
#140
0!
1'
0&
0$
