BCDto7Segment/bcdto7seg.v
module BCD_to_7_segment (a,b,c,d,e,f,g,q);
	output a,b,c,d,e,f,g;
	input [3:0] q;
	
	assign a = (q == 1 || q == 4) ? 1'b1 : 1'b0;
	assign b = (q == 5 || q == 6) ? 1'b1 : 1'b0;
	assign c = (q == 2) ? 1'b1 : 1'b0;
	assign d = (q == 1 || q == 4 || q == 7) ? 1'b1 : 1'b0;
	assign e = (q == 1 || q == 3 || q == 4 || q == 5 || q == 7 || q == 9) ? 1'b1 : 1'b0;
	assign f = (q == 1 || q == 2 || q == 3 || q == 7) ? 1'b1 : 1'b0;
	assign g = (q == 0 || q == 1 || q == 7) ? 1'b1 : 1'b0;

endmodule

BCDto7Segment/stimulus.v
module stimulus;
	wire a,b,c,d,e,f,g;
    reg [3:0] q;

    BCD_to_7_segment bcd (a,b,c,d,e,f,g,q);
	
	initial
		begin
			$dumpfile("BCDTimeDiagram.vcd");
			$dumpvars(0,stimulus);
            q = 4'b0000;
		end		
	initial
        begin
            #5 q = 4'b0001;
            #5 q = 4'b0010;
            #5 q = 4'b0011;
            #5 q = 4'b0100;
            #5 q = 4'b0101;
            #5 q = 4'b0110;
            #5 q = 4'b0111;
            #5 q = 4'b1000;
            #5 q = 4'b1001;
            #5 $finish;
        end
	initial 
		$monitor ($time, " a=%b b=%b c=%b d=%b e=%b f=%b g=%b q=%b",a,b,c,d,e,f,g,q);
endmodule

BCDto7Segment/BCDTimeDiagram.vcd
$date
	Fri Oct 07 16:13:10 2022
$end
$version
	Icarus Verilog
$end
$timescale
	1s
$end
$scope module stimulus $end
$var wire 1 ! g $end
$var wire 1 " f $end
$var wire 1 # e $end
$var wire 1 $ d $end
$var wire 1 % c $end
$var wire 1 & b $end
$var wire 1 ' a $end
$var reg 4 ( q [3:0] $end
$scope module bcd $end
$var wire 4 ) q [3:0] $end
$var wire 1 ! g $end
$var wire 1 " f $end
$var wire 1 # e $end
$var wire 1 $ d $end
$var wire 1 % c $end
$var wire 1 & b $end
$var wire 1 ' a $end
$upscope $end
$upscope $end
$enddefinitions $end
$comment Show the parameter values. $end
$dumpall
$end
#0
$dumpvars
b0 )
b0 (
0'
0&
0%
0$
0#
0"
1!
$end
#5
1#
1"
1$
1'
b1 (
b1 )
#10
0#
0$
0!
0'
1%
b10 (
b10 )
#15
1#
0%
b11 (
b11 )
#20
1$
0"
1'
b100 (
b100 )
#25
0$
0'
1&
b101 (
b101 )
#30
0#
b110 (
b110 )
#35
1#
0&
1$
1"
1!
b111 (
b111 )
#40
0#
0$
0"
0!
b1000 (
b1000 )
#45
1#
b1001 (
b1001 )
