sequence2bit8lv/levelMEM4bit/LvMEM4.v
module lvMEM (lv,up,on,setzero,reset,clk);
    output [3:0] lv;
    input up,on,setzero,reset,clk;
    wire t0,t1,t2,t3;

    // t0 in tff0
    wire t0_OtoO,t0_3AtoO,t0_AtoO,t0_NtoA,t0_Nto3A0,t0_Nto3A1,t0_4AtoN;
    or t0o0 (t0,t0_OtoO,on);
    or t0o1 (t0_OtoO,t0_3AtoO,t0_AtoO);
    and t0a0 (t0_AtoO,t0_NtoA,reset);
    not t0n0 (t0_NtoA,lv[0]);
    and3 t03A (t0_3AtoO,t0_Nto3A0,up,t0_Nto3A1);
    not t0n1 (t0_Nto3A0,t0_4AtoN);
    not t0n2 (t0_Nto3A1,reset);
    and4 t04A (t0_4AtoN,lv[0],lv[1],lv[2],lv[3]);

    // t1 in tff1
    wire t1_Nto3A,t1_3AtoN;
    and3 t13A0 (t1,lv[0],up,t1_Nto3A);
    not t1n (t1_Nto3A,t1_3AtoN);
    and3 t13A1 (t1_3AtoN,lv[1],lv[2],lv[3]);

    // t2 in tff2
    wire t2_Nto4A,t2_AtoN;
    and4 t24A (t2,up,lv[0],lv[1],t2_Nto4A);
    not t2n (t2_Nto4A,t2_AtoN);
    and t2a (t2_AtoN,lv[2],lv[3]);

    // t3 in tff3
    wire t3_4AtoA,t3_Nto4A;
    and t3a (t3,up,t3_4AtoA);
    and4 t34A (t3_4AtoA,lv[0],lv[1],lv[2],t3_Nto4A);
    not t3n (t3_Nto4A,lv[3]);

    wire reset1,reset2,reset3;
    or re1 (reset1,setzero,reset);
    or re2 (reset2,setzero,reset);
    or re3 (reset3,setzero,reset);
    T_FF tff0 (lv[0],t0,setzero,clk);
    T_FF tff1 (lv[1],t1,reset1,clk);
    T_FF tff2 (lv[2],t2,reset2,clk);
    T_FF tff3 (lv[3],t3,reset3,clk);
endmodule

module T_FF (q, t, reset, clk);
	output q;
	input t,reset,clk;
	wire d;

	xor x1(d,q,t);
	D_FF d1(q,d,reset,clk);
endmodule

module D_FF (q, d, reset, clk);
	output q;
	input d,reset,clk;
	reg q;
	
	always @(posedge reset or posedge clk)
		if (reset)
  			q <= 1'b0;
		else
  			q <= d;
endmodule

module and4 (out,a,b,c,d);
    output out;
    input a,b,c,d;
    wire an0,an1;

    and a0 (an0,a,b);
    and a1 (an1,c,d);
    and a2 (out,an0,an1);
endmodule

module and3 (out,a,b,c);
    output out;
    input a,b,c;
    wire an0;

    and a0 (an0,a,b);
    and a1 (out,an0,c);
endmodule

sequence2bit8lv/levelMEM4bit/stiLM.v
module stimulus;
	reg up,on,setzero,reset,clk;
	wire [3:0] lv;

    lvMEM LM (lv,up,on,setzero,reset,clk);
	
	initial
		begin
			$dumpfile("LMTD.vcd");
			$dumpvars(0,stimulus);
            setzero = 1'b1;
            up = 1'b0;
            on = 1'b0;
            reset = 1'b0;
			clk = 1'b1;     
		end
	always
		#5 clk = ~clk;
	initial
        begin
            #10 setzero = 1'b0;
            #10 on = 1'b1;
            #10 on = 1'b0;
            #10 up = 1'b1;
            #100 up = 1'b0;
            #30 reset = 1'b1;
            #20 up = 1'b1;
            #20 reset = 1'b0;
            #300 $finish;
        end
	initial 
		$monitor ($time, " lv0=%b lv1=%b lv2=%b lv3=%b up=%d on=%d setzero=%d reset=%d CLK=%d",lv[0],lv[1],lv[2],lv[3],up,on,setzero,reset,clk);
endmodule

sequence2bit8lv/levelMEM4bit/LMTD.vcd
$date
	Thu Oct 13 20:17:47 2022
$end
$version
	Icarus Verilog
$end
$timescale
	1s
$end
$scope module stimulus $end
$var wire 4 ! lv [3:0] $end
$var reg 1 " clk $end
$var reg 1 # on $end
$var reg 1 $ reset $end
$var reg 1 % setzero $end
$var reg 1 & up $end
$scope module LM $end
$var wire 1 " clk $end
$var wire 1 # on $end
$var wire 1 $ reset $end
$var wire 1 ' reset1 $end
$var wire 1 ( reset2 $end
$var wire 1 ) reset3 $end
$var wire 1 % setzero $end
$var wire 1 * t0 $end
$var wire 1 + t0_AtoO $end
$var wire 1 , t0_Nto3A0 $end
$var wire 1 - t0_Nto3A1 $end
$var wire 1 . t0_NtoA $end
$var wire 1 / t0_OtoO $end
$var wire 1 0 t1_Nto3A $end
$var wire 1 1 t2_AtoN $end
$var wire 1 2 t2_Nto4A $end
$var wire 1 3 t3 $end
$var wire 1 4 t3_Nto4A $end
$var wire 1 & up $end
$var wire 1 5 t3_4AtoA $end
$var wire 1 6 t2 $end
$var wire 1 7 t1_3AtoN $end
$var wire 1 8 t1 $end
$var wire 1 9 t0_4AtoN $end
$var wire 1 : t0_3AtoO $end
$var wire 4 ; lv [3:0] $end
$scope module t03A $end
$var wire 1 , a $end
$var wire 1 < an0 $end
$var wire 1 & b $end
$var wire 1 - c $end
$var wire 1 : out $end
$upscope $end
$scope module t04A $end
$var wire 1 = a $end
$var wire 1 > an0 $end
$var wire 1 ? an1 $end
$var wire 1 @ b $end
$var wire 1 A c $end
$var wire 1 B d $end
$var wire 1 9 out $end
$upscope $end
$scope module t13A0 $end
$var wire 1 C a $end
$var wire 1 D an0 $end
$var wire 1 & b $end
$var wire 1 0 c $end
$var wire 1 8 out $end
$upscope $end
$scope module t13A1 $end
$var wire 1 E a $end
$var wire 1 F an0 $end
$var wire 1 G b $end
$var wire 1 H c $end
$var wire 1 7 out $end
$upscope $end
$scope module t24A $end
$var wire 1 & a $end
$var wire 1 I an0 $end
$var wire 1 J an1 $end
$var wire 1 K b $end
$var wire 1 L c $end
$var wire 1 2 d $end
$var wire 1 6 out $end
$upscope $end
$scope module t34A $end
$var wire 1 M a $end
$var wire 1 N an0 $end
$var wire 1 O an1 $end
$var wire 1 P b $end
$var wire 1 Q c $end
$var wire 1 4 d $end
$var wire 1 5 out $end
$upscope $end
$scope module tff0 $end
$var wire 1 " clk $end
$var wire 1 R d $end
$var wire 1 % reset $end
$var wire 1 * t $end
$var wire 1 S q $end
$scope module d1 $end
$var wire 1 " clk $end
$var wire 1 R d $end
$var wire 1 % reset $end
$var reg 1 S q $end
$upscope $end
$upscope $end
$scope module tff1 $end
$var wire 1 " clk $end
$var wire 1 T d $end
$var wire 1 ' reset $end
$var wire 1 8 t $end
$var wire 1 U q $end
$scope module d1 $end
$var wire 1 " clk $end
$var wire 1 T d $end
$var wire 1 ' reset $end
$var reg 1 U q $end
$upscope $end
$upscope $end
$scope module tff2 $end
$var wire 1 " clk $end
$var wire 1 V d $end
$var wire 1 ( reset $end
$var wire 1 6 t $end
$var wire 1 W q $end
$scope module d1 $end
$var wire 1 " clk $end
$var wire 1 V d $end
$var wire 1 ( reset $end
$var reg 1 W q $end
$upscope $end
$upscope $end
$scope module tff3 $end
$var wire 1 " clk $end
$var wire 1 X d $end
$var wire 1 ) reset $end
$var wire 1 3 t $end
$var wire 1 Y q $end
$scope module d1 $end
$var wire 1 " clk $end
$var wire 1 X d $end
$var wire 1 ) reset $end
$var reg 1 Y q $end
$upscope $end
$upscope $end
$upscope $end
$upscope $end
$enddefinitions $end
$comment Show the parameter values. $end
$dumpall
$end
#0
$dumpvars
0Y
0X
0W
0V
0U
0T
0S
0R
0Q
0P
0O
0N
0M
0L
0K
0J
0I
0H
0G
0F
0E
0D
0C
0B
0A
0@
0?
0>
0=
0<
b0 ;
0:
09
08
07
06
05
14
03
12
01
10
0/
1.
1-
1,
0+
0*
1)
1(
1'
0&
1%
0$
0#
1"
b0 !
$end
#5
0"
#10
0'
0(
0)
1"
0%
#15
0"
#20
1R
1*
1"
1#
#25
0"
#30
0.
1M
1K
1C
1=
b1 !
b1 ;
1S
1R
0*
1"
0#
#35
0"
#40
0R
1*
1/
1T
1:
18
1<
1D
1I
1"
1&
#45
0"
#50
08
0I
0D
1.
1J
1R
0M
0K
0C
0=
1T
1P
1L
1E
1@
0S
b10 !
b10 ;
1U
1"
#55
0"
#60
1V
0T
16
18
1N
1I
1D
1>
0.
0R
1M
1K
1C
1=
b11 !
b11 ;
1S
1"
#65
0"
#70
08
06
0I
0D
1.
0N
0J
0>
1O
1R
0M
0K
0C
0=
0T
0P
0L
0E
0@
1V
1Q
1G
1A
0S
0U
b100 !
b100 ;
1W
1"
#75
0"
#80
1T
18
1I
1D
0.
0R
1M
1K
1C
1=
b101 !
b101 ;
1S
1"
#85
0"
#90
08
0I
0D
1.
1J
1F
1R
0M
0K
0C
0=
1T
1P
1L
1E
1@
0S
b110 !
b110 ;
1U
1"
#95
0"
#100
1X
13
0V
0T
15
16
18
1N
1I
1D
1>
0.
0R
1M
1K
1C
1=
b111 !
b111 ;
1S
1"
#105
0"
#110
03
08
06
05
10
0I
0D
1.
0N
0J
0>
0O
0F
04
07
1R
0M
0K
0C
0=
0T
0P
0L
0E
0@
0V
0Q
0G
0A
1X
1H
1B
0S
0U
0W
b1000 !
b1000 ;
1Y
1"
#115
0"
#120
1T
18
1I
1D
0.
0R
1M
1K
1C
1=
b1001 !
b1001 ;
1S
1"
#125
0"
#130
08
0I
0D
1.
1J
1R
0M
0K
0C
0=
1T
1P
1L
1E
1@
0S
b1010 !
b1010 ;
1U
1"
#135
0"
#140
1N
1>
0.
1M
1K
1C
1=
b1011 !
b1011 ;
1S
1R
0*
0/
0:
0<
1"
0&
#145
0"
#150
1"
#155
0"
#160
1"
#165
0"
#170
0N
0J
0>
14
0T
0P
0L
0E
0@
0X
0H
0B
0U
b1 !
b1 ;
0Y
0-
1'
1(
1)
1"
1$
#175
0"
#180
1"
#185
0"
#190
1T
18
1<
1D
1I
1"
1&
#195
0"
#200
1"
#205
0"
#210
1V
16
1N
1J
1>
0T
1P
1L
1E
1@
b11 !
b11 ;
1U
0R
1*
1/
1:
1-
0'
0(
0)
1"
0$
#215
0"
#220
08
06
0I
0D
1.
0N
0J
0>
1O
1R
0M
0K
0C
0=
0T
0P
0L
0E
0@
1V
1Q
1G
1A
0S
0U
b100 !
b100 ;
1W
1"
#225
0"
#230
1T
18
1I
1D
0.
0R
1M
1K
1C
1=
b101 !
b101 ;
1S
1"
#235
0"
#240
08
0I
0D
1.
1J
1F
1R
0M
0K
0C
0=
1T
1P
1L
1E
1@
0S
b110 !
b110 ;
1U
1"
#245
0"
#250
1X
13
0V
0T
15
16
18
1N
1I
1D
1>
0.
0R
1M
1K
1C
1=
b111 !
b111 ;
1S
1"
#255
0"
#260
03
08
06
05
10
0I
0D
1.
0N
0J
0>
0O
0F
04
07
1R
0M
0K
0C
0=
0T
0P
0L
0E
0@
0V
0Q
0G
0A
1X
1H
1B
0S
0U
0W
b1000 !
b1000 ;
1Y
1"
#265
0"
#270
1T
18
1I
1D
0.
0R
1M
1K
1C
1=
b1001 !
b1001 ;
1S
1"
#275
0"
#280
08
0I
0D
1.
1J
1R
0M
0K
0C
0=
1T
1P
1L
1E
1@
0S
b1010 !
b1010 ;
1U
1"
#285
0"
#290
1V
0T
16
18
1N
1I
1D
1>
0.
0R
1M
1K
1C
1=
b1011 !
b1011 ;
1S
1"
#295
0"
#300
08
06
02
0I
0D
1.
0N
0J
0>
11
1?
1R
0M
0K
0C
0=
0T
0P
0L
0E
0@
1V
1Q
1G
1A
0S
0U
b1100 !
b1100 ;
1W
1"
#305
0"
#310
1T
18
1I
1D
0.
0R
1M
1K
1C
1=
b1101 !
b1101 ;
1S
1"
#315
0"
#320
00
08
17
0I
0D
1.
1F
1R
0M
0K
0C
0=
1T
1P
1L
1E
1@
0S
b1110 !
b1110 ;
1U
1"
#325
0"
#330
0*
0/
0:
0<
0,
19
1N
1I
1D
1>
0.
1R
1M
1K
1C
1=
b1111 !
b1111 ;
1S
1"
