S-R_Latch/SRLatch.v
module sr_latch(
    q,qn,r,s
);

input r,s;

output q,qn;

nor nor1(q,r,qn);
nor nor2(qn,q,s);

endmodule

S-R_Latch/SRLatchStimulus.v
module stimulus;
	reg s,r;
	wire q,qn;
	// instantiate the design block
	sr_latch sr(q,qn,r,s);
	
	// control the signals that drives the design block
	initial
		begin
			$dumpfile("SRLatchTimeDiagram.vcd");
			$dumpvars(0,stimulus);
			s = 1'b0;
			r = 1'b0;
		end		
	initial
	begin
		#5 begin
			s = 1'b1;
			r = 1'b0;
			end
		#5 begin
			s = 1'b0;
			r = 1'b0;
			end
        #5 begin
			s = 1'b0;
			r = 1'b1;
			end
        #5 begin
			s = 1'b0;
			r = 1'b0;
			end
        #5 begin
			s = 1'b1;
			r = 1'b0;
			end
        #5 begin
			s = 1'b0;
			r = 1'b1;
			end
        #5 begin
			s = 1'b1;
			r = 1'b1;
			end
        #5 begin
			s = 1'b0;
			r = 1'b0;
			end
		#45 $finish;
	end
	initial 
		$monitor ($time, " Output S=%d R=%d Q=%d QN=%d",s,r,q,qn);
 endmodule

S-R_Latch/SRLatchTimeDiagram.vcd
$date
	Mon Sep 26 22:22:43 2022
$end
$version
	Icarus Verilog
$end
$timescale
	1s
$end
$scope module stimulus $end
$var wire 1 ! qn $end
$var wire 1 " q $end
$var reg 1 # r $end
$var reg 1 $ s $end
$scope module sr $end
$var wire 1 " q $end
$var wire 1 ! qn $end
$var wire 1 # r $end
$var wire 1 $ s $end
$upscope $end
$upscope $end
$enddefinitions $end
$comment Show the parameter values. $end
$dumpall
$end
#0
$dumpvars
0$
0#
x"
x!
$end
#5
1"
0!
1$
#10
0$
#15
1!
0"
1#
#20
0#
#25
1"
0!
1$
#30
1!
0"
1#
0$
#35
0!
1$
#40
1!
0#
0$
