sequence2bit8lv/countup4bit/C4B.v
module C4B (q,en,reset,clk);
	output [3:0] q;
	input en,reset,clk;
	wire t1,t2,t3;

    and a1 (t1,q[0],en);
    and3 a2 (t2,q[0],q[1],en);
    and a3 (t3,q[2],t2);
	T_FF tff0 (q[0],en,reset,clk);
	T_FF tff1 (q[1],t1,reset,clk);
    T_FF tff2 (q[2],t2,reset,clk);
    T_FF tff3 (q[3],t3,reset,clk);
endmodule

module T_FF (q, t, reset, clk);
	output q;
	input t,reset,clk;
	wire d;

	xor x1(d,q,t);
	D_FF d1(q,d,reset,clk);
endmodule

module D_FF (q, d, reset, clk);
	output q;
	input d,reset,clk;
	reg q;
	
	always @(posedge reset or posedge clk)
		if (reset)
  			q <= 1'b0;
		else
  			q <= d;
endmodule

module and3 (out,a,b,c);
    output out;
    input a,b,c;
    wire an0;

    and a0 (an0,a,b);
    and a1 (out,an0,c);
endmodule

sequence2bit8lv/countup4bit/stiC4B.v
module stimulus;
	reg en,reset,clk;
	wire [3:0] q;

    C4B a (q,en,reset,clk);
	
	initial
		begin
			$dumpfile("C4BTD.vcd");
			$dumpvars(0,stimulus);
            en = 1'b0;
            reset = 1'b1;
			clk = 1'b1;     
		end
	always
		#5 clk = ~clk;
	initial
        begin
            #10 reset = 1'b0;
            #10 en = 1'b1;
            #200 en = 1'b0;
            #50 $finish;
        end
endmodule

sequence2bit8lv/countup4bit/C4BTD.vcd
$date
	Thu Oct 13 23:38:37 2022
$end
$version
	Icarus Verilog
$end
$timescale
	1s
$end
$scope module stimulus $end
$var wire 4 ! q [3:0] $end
$var reg 1 " clk $end
$var reg 1 # en $end
$var reg 1 $ reset $end
$scope module a $end
$var wire 1 " clk $end
$var wire 1 # en $end
$var wire 1 $ reset $end
$var wire 1 % t1 $end
$var wire 1 & t3 $end
$var wire 1 ' t2 $end
$var wire 4 ( q [3:0] $end
$scope module a2 $end
$var wire 1 ) a $end
$var wire 1 * an0 $end
$var wire 1 + b $end
$var wire 1 # c $end
$var wire 1 ' out $end
$upscope $end
$scope module tff0 $end
$var wire 1 " clk $end
$var wire 1 , d $end
$var wire 1 $ reset $end
$var wire 1 # t $end
$var wire 1 - q $end
$scope module d1 $end
$var wire 1 " clk $end
$var wire 1 , d $end
$var wire 1 $ reset $end
$var reg 1 - q $end
$upscope $end
$upscope $end
$scope module tff1 $end
$var wire 1 " clk $end
$var wire 1 . d $end
$var wire 1 $ reset $end
$var wire 1 % t $end
$var wire 1 / q $end
$scope module d1 $end
$var wire 1 " clk $end
$var wire 1 . d $end
$var wire 1 $ reset $end
$var reg 1 / q $end
$upscope $end
$upscope $end
$scope module tff2 $end
$var wire 1 " clk $end
$var wire 1 0 d $end
$var wire 1 $ reset $end
$var wire 1 ' t $end
$var wire 1 1 q $end
$scope module d1 $end
$var wire 1 " clk $end
$var wire 1 0 d $end
$var wire 1 $ reset $end
$var reg 1 1 q $end
$upscope $end
$upscope $end
$scope module tff3 $end
$var wire 1 " clk $end
$var wire 1 2 d $end
$var wire 1 $ reset $end
$var wire 1 & t $end
$var wire 1 3 q $end
$scope module d1 $end
$var wire 1 " clk $end
$var wire 1 2 d $end
$var wire 1 $ reset $end
$var reg 1 3 q $end
$upscope $end
$upscope $end
$upscope $end
$upscope $end
$enddefinitions $end
$comment Show the parameter values. $end
$dumpall
$end
#0
$dumpvars
03
02
01
00
0/
0.
0-
0,
0+
0*
0)
b0 (
0'
0&
0%
1$
0#
1"
b0 !
$end
#5
0"
#10
1"
0$
#15
0"
#20
1.
1%
1)
b1 !
b1 (
1-
0,
1"
1#
#25
0"
#30
0%
1.
1+
1,
0)
1/
b10 !
b10 (
0-
1"
#35
0"
#40
10
1'
0.
1*
1%
0,
1)
b11 !
b11 (
1-
1"
#45
0"
#50
02
0'
0&
0*
0%
10
0.
0+
1,
0)
11
0/
b100 !
b100 (
0-
1"
#55
0"
#60
1.
1%
0,
1)
b101 !
b101 (
1-
1"
#65
0"
#70
0%
1.
1+
1,
0)
1/
b110 !
b110 (
0-
1"
#75
0"
#80
12
00
1&
1'
0.
1*
1%
0,
1)
b111 !
b111 (
1-
1"
#85
0"
#90
0'
0&
0*
0%
12
00
0.
0+
1,
0)
13
01
0/
b1000 !
b1000 (
0-
1"
#95
0"
#100
1.
1%
0,
1)
b1001 !
b1001 (
1-
1"
#105
0"
#110
0%
1.
1+
1,
0)
1/
b1010 !
b1010 (
0-
1"
#115
0"
#120
10
1'
0.
1*
1%
0,
1)
b1011 !
b1011 (
1-
1"
#125
0"
#130
12
0'
0&
0*
0%
10
0.
0+
1,
0)
11
0/
b1100 !
b1100 (
0-
1"
#135
0"
#140
1.
1%
0,
1)
b1101 !
b1101 (
1-
1"
#145
0"
#150
0%
1.
1+
1,
0)
1/
b1110 !
b1110 (
0-
1"
#155
0"
#160
02
00
1&
1'
0.
1*
1%
0,
1)
b1111 !
b1111 (
1-
1"
#165
0"
#170
0'
0&
0*
0%
02
00
0.
0+
1,
0)
03
01
0/
b0 !
b0 (
0-
1"
#175
0"
#180
1.
1%
0,
1)
b1 !
b1 (
1-
1"
#185
0"
#190
0%
1.
1+
1,
0)
1/
b10 !
b10 (
0-
1"
#195
0"
#200
10
1'
0.
1*
1%
0,
1)
b11 !
b11 (
1-
1"
#205
0"
#210
02
0'
0&
0*
0%
10
0.
0+
1,
0)
11
0/
b100 !
b100 (
0-
1"
#215
0"
#220
0,
1"
0#
