sequence2bit8lv/dataStop4bit/Dstop4.v
module DS (d,b,en,reset,clk);
    output [15:0] d;
    input [3:0] b;
    input en,reset,clk;
    reg [15:0] d;

    always @(posedge en or posedge reset or posedge clk)
    begin 
        if(reset)
            d <= 0;
        else
        begin
            if(en)
            begin
                case(b)
                    0 : d <= 16'b0000_0000_0000_0001;
                    1 : d <= 16'b0000_0000_0000_0011;
                    2 : d <= 16'b0000_0000_0000_0111;
                    3 : d <= 16'b0000_0000_0000_1111;
                    4 : d <= 16'b0000_0000_0001_1111;
                    5 : d <= 16'b0000_0000_0011_1111;
                    6 : d <= 16'b0000_0000_0111_1111;
                    7 : d <= 16'b0000_0000_1111_1111;
                    8 : d <= 16'b0000_0001_1111_1111;
                    9 : d <= 16'b0000_0011_1111_1111;
                    10 : d <= 16'b0000_0111_1111_1111;
                    11 : d <= 16'b0000_1111_1111_1111;
                    12 : d <= 16'b0001_1111_1111_1111;
                    13 : d <= 16'b0011_1111_1111_1111;
                    14 : d <= 16'b0111_1111_1111_1111;
                    15 : d <= 16'b1111_1111_1111_1111;
                    default : d <= 16'b0000_0000_0000_0000;
                endcase
            end
            else
                d <= d;
        end
    end
endmodule

module reg4bit (q,d,en,reset,clk);
    output [3:0] q;
    input [3:0] d;
    input en,reset,clk;

    reg1bit reg0 (q[0],d[0],en,reset,clk);
    reg1bit reg1 (q[1],d[1],en,reset,clk);
    reg1bit reg2 (q[2],d[2],en,reset,clk);
    reg1bit reg3 (q[3],d[3],en,reset,clk);
endmodule

module reg1bit (q,d,en,reset,clk);
    output q;
    input d,en,reset,clk;
    wire d0,AtoO0,AtoO1,NtoA0;

    or or0 (d0,AtoO0,AtoO1);
    and and1 (AtoO1,d,en);
    and and0 (AtoO0,q,NtoA0);
    not not0 (NtoA0,en);
    D_FF dff (q,d0,reset,clk);
endmodule

module D_FF (q, d, reset, clk);
	output q;
	input d,reset,clk;
	reg q;
	
	always @(posedge reset or posedge clk)
		if (reset)
  			q <= 1'b0;
		else
  			q <= d;
endmodule

sequence2bit8lv/dataStop4bit/stiDS.v
module stimulus;
	reg en,reset,clk;
    reg [3:0] b;
	wire [15:0] d;

    DS dstop (d,b,en,reset,clk);
	
	initial
		begin
			$dumpfile("DSTD.vcd");
			$dumpvars(0,stimulus);
            b = 4'b0000;
            en = 1'b0;
            reset = 1'b1;
			clk = 1'b1;     
		end
	always
		#5 clk = ~clk;
	initial
        begin
            #10 reset = 1'b0;
            #10 en = 1'b1;
            #10 b = 1;
            #10 b = 2;
            #10 b = 3;
            #10 b = 4;
            #10 b = 5;
            #10 b = 6;
            #10 b = 7;
            #10 b = 8;
            #10 b = 9;
            #10 b = 10;
            #10 en = 1'b0;
            #50 en = 1'b1;
            #10 b = 11;
            #10 b = 12;
            #10 b = 13;
            #10 b = 14;
            #10 b = 15;
            #10 reset = 1'b1;
            #50 reset = 1'b0;
            #10 en = 1'b1;
            #10 b = 10;
            #50 $finish;
        end
endmodule

sequence2bit8lv/dataStop4bit/DSTD.vcd
$date
	Thu Oct 13 21:37:26 2022
$end
$version
	Icarus Verilog
$end
$timescale
	1s
$end
$scope module stimulus $end
$var wire 16 ! d [15:0] $end
$var reg 4 " b [3:0] $end
$var reg 1 # clk $end
$var reg 1 $ en $end
$var reg 1 % reset $end
$scope module dstop $end
$var wire 4 & b [3:0] $end
$var wire 1 # clk $end
$var wire 1 $ en $end
$var wire 1 % reset $end
$var reg 16 ' d [15:0] $end
$upscope $end
$upscope $end
$enddefinitions $end
$comment Show the parameter values. $end
$dumpall
$end
#0
$dumpvars
b0 '
b0 &
1%
0$
1#
b0 "
b0 !
$end
#5
0#
#10
1#
0%
#15
0#
#20
b1 !
b1 '
1#
1$
#25
0#
#30
b11 !
b11 '
1#
b1 "
b1 &
#35
0#
#40
b111 !
b111 '
1#
b10 "
b10 &
#45
0#
#50
b1111 !
b1111 '
1#
b11 "
b11 &
#55
0#
#60
b11111 !
b11111 '
1#
b100 "
b100 &
#65
0#
#70
b111111 !
b111111 '
1#
b101 "
b101 &
#75
0#
#80
b1111111 !
b1111111 '
1#
b110 "
b110 &
#85
0#
#90
b11111111 !
b11111111 '
1#
b111 "
b111 &
#95
0#
#100
b111111111 !
b111111111 '
1#
b1000 "
b1000 &
#105
0#
#110
b1111111111 !
b1111111111 '
1#
b1001 "
b1001 &
#115
0#
#120
b11111111111 !
b11111111111 '
1#
b1010 "
b1010 &
#125
0#
#130
1#
0$
#135
0#
#140
1#
#145
0#
#150
1#
#155
0#
#160
1#
#165
0#
#170
1#
#175
0#
#180
1#
1$
#185
0#
#190
b111111111111 !
b111111111111 '
1#
b1011 "
b1011 &
#195
0#
#200
b1111111111111 !
b1111111111111 '
1#
b1100 "
b1100 &
#205
0#
#210
b11111111111111 !
b11111111111111 '
1#
b1101 "
b1101 &
#215
0#
#220
b111111111111111 !
b111111111111111 '
1#
b1110 "
b1110 &
#225
0#
#230
b1111111111111111 !
b1111111111111111 '
1#
b1111 "
b1111 &
#235
0#
#240
b0 !
b0 '
1#
1%
#245
0#
#250
1#
#255
0#
#260
1#
#265
0#
#270
1#
#275
0#
#280
1#
#285
0#
#290
b1111111111111111 !
b1111111111111111 '
1#
0%
#295
0#
#300
1#
#305
0#
#310
b11111111111 !
b11111111111 '
1#
b1010 "
b1010 &
