bcd_to_7_segment/bcd7segment.v
module BCD_to_7_segment (a,b,c,d,e,f,g,q);
	output a,b,c,d,e,f,g;
	input [3:0] q;

	assign a = (q == 1 || q == 4) ? 1'b1 : 1'b0;
	assign b = (q == 5 || q == 6) ? 1'b1 : 1'b0;
	assign c = (q == 2) ? 1'b1 : 1'b0;
	assign d = (q == 1 || q == 4 || q == 7) ? 1'b1 : 1'b0;
	assign e = (q == 1 || q == 3 || q == 4 || q == 5 || q == 7 || q == 9) ? 1'b1 : 1'b0;
	assign f = (q == 1 || q == 2 || q == 3 || q == 7) ? 1'b1 : 1'b0;
	assign g = (q == 0 || q == 1 || q == 7) ? 1'b1 : 1'b0;

endmodule

bcd_to_7_segment/stimulus.v
module stimulus;
	wire a,b,c,d,e,f,g;
    reg [3:0] q;

    BCD_to_7_segment bcd7 (a,b,c,d,e,f,g,q);
	
	initial
		begin
			$dumpfile("BCD7TimeDiagram.vcd");
			$dumpvars(0,stimulus);
            q = 4'b0000;
		end

	initial
        begin
            #5 q = 1;
            #5 q = 2;
            #5 q = 3;
            #5 q = 4;
            #5 q = 5;
            #5 q = 6;
            #5 q = 7;
            #5 q = 8;
            #5 q = 9;
            #5 $finish;
        end
	initial 
		$monitor ($time, " a=%d b=%d c=%d d=%d e=%d f=%d g=%d q3=%b q2=%b q1=%b q0=%b",a,b,c,d,e,f,g,q[3],q[2],q[1],q[0]);
endmodule

bcd_to_7_segment/BCD7TimeDiagram.vcd
$date
	Sun Oct 02 19:05:42 2022
$end
$version
	Icarus Verilog
$end
$timescale
	1s
$end
$scope module stimulus $end
$var wire 1 ! g $end
$var wire 1 " f $end
$var wire 1 # e $end
$var wire 1 $ d $end
$var wire 1 % c $end
$var wire 1 & b $end
$var wire 1 ' a $end
$var reg 4 ( q [3:0] $end
$scope module bcd7 $end
$var wire 4 ) q [3:0] $end
$var wire 1 ! g $end
$var wire 1 " f $end
$var wire 1 # e $end
$var wire 1 $ d $end
$var wire 1 % c $end
$var wire 1 & b $end
$var wire 1 ' a $end
$upscope $end
$upscope $end
$enddefinitions $end
$comment Show the parameter values. $end
$dumpall
$end
#0
$dumpvars
b0 )
b0 (
0'
0&
0%
0$
0#
0"
1!
$end
#5
1#
1"
1$
1'
b1 (
b1 )
#10
0#
0$
0!
0'
1%
b10 (
b10 )
#15
1#
0%
b11 (
b11 )
#20
1$
0"
1'
b100 (
b100 )
#25
0$
0'
1&
b101 (
b101 )
#30
0#
b110 (
b110 )
#35
1#
0&
1$
1"
1!
b111 (
b111 )
#40
0#
0$
0"
0!
b1000 (
b1000 )
#45
1#
b1001 (
b1001 )
