lab7/countup2bit.v
//-----------------------------------------------------
 // Design Name : 2-Bit Synchronous Count Up 
 // File Name   : Count2BitSync.v
 // Function    : Using Synchronous Sequential Circuit Design to create 2 bit count up on CPLD
 // Coder       : Paskorn Champrasert
 // Date 		: Sept 27, 2022
 //-----------------------------------------------------
 
module countup2bit (a,b,c,d,e,f,g, q, clk, reset);
	output a,b,c,d,e,f,g;
	output [1:0] q; // MSB [...] LSB
	input clk, reset;
	wire q0;

		T_FF tff0 (q[0], 1'b1, clk, reset);
		T_FF tff1 (q[1], q[0], clk, reset);
		BCD_to_7_segment bcds (a,b,c,d,e,f,g,{2'b00,q});
			
endmodule

module BCD_to_7_segment (a,b,c,d,e,f,g,q);
	output a,b,c,d,e,f,g;
	input [3:0] q;
	
	assign a = (q == 1 || q == 4) ? 1'b1 : 1'b0;
	assign b = (q == 5 || q == 6) ? 1'b1 : 1'b0;
	assign c = (q == 2) ? 1'b1 : 1'b0;
	assign d = (q == 1 || q == 4 || q == 7) ? 1'b1 : 1'b0;
	assign e = (q == 1 || q == 3 || q == 4 || q == 5 || q == 7 || q == 9) ? 1'b1 : 1'b0;
	assign f = (q == 1 || q == 2 || q == 3 || q == 7) ? 1'b1 : 1'b0;
	assign g = (q == 0 || q == 1 || q == 7) ? 1'b1 : 1'b0;

endmodule

module T_FF (q, t, clk, reset);
	output q;
	input t,clk,reset;
	wire d;
		xor x1(d,q,t);
		D_FF d1(q,d,clk,reset);
endmodule

module D_FF (q, d, clk, reset);
	output q;
	input d,clk,reset;
	reg q;
	
	always @(posedge reset or negedge clk)
		if (reset)
  			q <= 1'b0;
		else
  			q <= d;
endmodule

lab7/countup_stimulus.v
module stimulus;
	reg clk,reset;
	wire a,b,c,d,e,f,g;
    wire [1:0] q;

    countup2bit c2b (a,b,c,d,e,f,g, q, clk, reset);
	
	initial
		begin
			$dumpfile("CountUpTimeDiagram.vcd");
			$dumpvars(0,stimulus);
			reset = 1'b0;
			clk   = 1'b0;
		end		
	always 
		#10 clk = ~clk;
	initial
        begin
            #80 begin
                reset = 1'b1;
                end
            #100 $finish;
        end
	initial 
		$monitor ($time, "CLK=%d reset=%d q1=$d q0=%d a=%d b=%d c=%d d=%d e=%d f=%d g=%d",clk,reset,q[1],q[0],a,b,c,d,e,f,g);
endmodule

lab7/CountUpTimeDiagram.vcd
$date
	Sun Oct 02 18:33:44 2022
$end
$version
	Icarus Verilog
$end
$timescale
	1s
$end
$scope module stimulus $end
$var wire 2 ! q [1:0] $end
$var wire 1 " g $end
$var wire 1 # f $end
$var wire 1 $ e $end
$var wire 1 % d $end
$var wire 1 & c $end
$var wire 1 ' b $end
$var wire 1 ( a $end
$var reg 1 ) clk $end
$var reg 1 * reset $end
$scope module c2b $end
$var wire 1 ) clk $end
$var wire 1 * reset $end
$var wire 2 + q [1:0] $end
$var wire 1 " g $end
$var wire 1 # f $end
$var wire 1 $ e $end
$var wire 1 % d $end
$var wire 1 & c $end
$var wire 1 ' b $end
$var wire 1 ( a $end
$scope module bcds $end
$var wire 4 , q [3:0] $end
$var wire 1 " g $end
$var wire 1 # f $end
$var wire 1 $ e $end
$var wire 1 % d $end
$var wire 1 & c $end
$var wire 1 ' b $end
$var wire 1 ( a $end
$upscope $end
$scope module tff0 $end
$var wire 1 ) clk $end
$var wire 1 - d $end
$var wire 1 * reset $end
$var wire 1 . t $end
$var wire 1 / q $end
$scope module d1 $end
$var wire 1 ) clk $end
$var wire 1 - d $end
$var wire 1 * reset $end
$var reg 1 / q $end
$upscope $end
$upscope $end
$scope module tff1 $end
$var wire 1 ) clk $end
$var wire 1 0 d $end
$var wire 1 * reset $end
$var wire 1 1 t $end
$var wire 1 2 q $end
$scope module d1 $end
$var wire 1 ) clk $end
$var wire 1 0 d $end
$var wire 1 * reset $end
$var reg 1 2 q $end
$upscope $end
$upscope $end
$upscope $end
$upscope $end
$enddefinitions $end
$comment Show the parameter values. $end
$dumpall
$end
#0
$dumpvars
02
01
00
0/
1.
1-
b0 ,
b0 +
1*
0)
0(
0'
0&
0%
0$
0#
1"
b0 !
$end
#5
1)
#10
0)
#15
1)
#20
0)
#25
1)
#30
0)
#35
1)
#40
0)
#45
1)
#50
1$
1#
1%
10
1(
0-
11
b1 ,
b1 !
b1 +
1/
0)
0*
#55
1)
#60
0$
0%
0"
0(
1-
01
1&
10
0/
b10 ,
b10 !
b10 +
12
0)
#65
1)
#70
1$
00
0-
11
0&
b11 ,
b11 !
b11 +
1/
0)
#75
1)
#80
0$
0#
1"
1-
01
00
0/
b0 ,
b0 !
b0 +
02
0)
#85
1)
#90
1$
1#
1%
10
1(
0-
11
b1 ,
b1 !
b1 +
1/
0)
#95
1)
#100
0$
0#
0%
00
0(
1-
01
b0 ,
b0 !
b0 +
0/
0)
1*
#105
1)
0*
#110
1$
1#
1%
10
1(
0-
11
b1 ,
b1 !
b1 +
1/
0)
#115
1)
#120
0$
0%
0"
0(
1-
01
1&
10
0/
b10 ,
b10 !
b10 +
12
0)
#125
1)
#130
1$
00
0-
11
0&
b11 ,
b11 !
b11 +
1/
0)
#135
1)
#140
0$
0#
1"
1-
01
00
0/
b0 ,
b0 !
b0 +
02
0)
#145
1)
#150
1$
1#
1%
10
1(
0-
11
b1 ,
b1 !
b1 +
1/
0)
